lfsr.sv
module lfsr #(
    parameter int c_LFSR_BITS = 7,
    parameter logic [c_LFSR_BITS-1:0] c_LFSR_SEED = 'h1 // since all-zero seed is not allowed
) (
    input logic i_clock,
    input logic i_reset, // active-low reset to improve noise immunity
    input logic i_load_enable,
    input logic i_load_bit,
    output logic o_last_lfsr_bit
);
    logic [c_LFSR_BITS-1:0] lfsr_bits;
    logic xor_gate;

    // select bit to XOR; see README for details
    always_comb begin
        unique case (c_LFSR_BITS)
            // PRBS-7 polynomial is x**7 + x**6 + 1
            7: xor_gate = lfsr_bits[6] ^ lfsr_bits[5];
            // PRBS-31 polynomial is x**31 + x**28 + 1
            31: xor_gate = lfsr_bits[30] ^ lfsr_bits[27];

            default: xor_gate = '0;    
        endcase
    end
    
    always_ff @(posedge i_clock or negedge i_reset) begin
        if (!i_reset) lfsr_bits <= c_LFSR_SEED;
        else if (i_load_enable) lfsr_bits <= {lfsr_bits[c_LFSR_BITS-2:0], i_load_bit};
        else lfsr_bits <= {lfsr_bits[c_LFSR_BITS-2:0], xor_gate}; 
    end
    assign o_last_lfsr_bit = lfsr_bits[c_LFSR_BITS-1]; // transmit 1 bit per clock cycle
endmodule

sim/lfsr_tb.sv
`default_nettype none

module lfsr_tb ();
    localparam c_LFSR_BITS = 7; // to simulate quicker 
    int c_LFSR_PERIOD = (2**c_LFSR_BITS) - 1; // to simulate quicker 
    localparam c_WAIT_FOR_SIGNALS_TO_SETTLE = 1;

    logic r_tb_clock = 1'b0;
    always #5 r_tb_clock <= !r_tb_clock;
    logic r_tb_reset = 1'b1;

    logic r_tb_load_enable = 1'b0;
    logic r_tb_load_bit = 1'b0;
    logic r_tb_last_lfsr_bit;
    logic [c_LFSR_BITS-1:0] r_tb_expected_next_state;

    lfsr #(.c_LFSR_BITS(c_LFSR_BITS)) UUT (
        .i_clock(r_tb_clock),
        .i_reset(r_tb_reset),
        .i_load_enable(r_tb_load_enable),
        .i_load_bit(r_tb_load_bit),
        .o_last_lfsr_bit(r_tb_last_lfsr_bit)
    );

    function automatic [c_LFSR_BITS-1:0] get_next_state (input [c_LFSR_BITS-1:0] current_state);
        logic xor_gate;
        /* verilator lint_off SELRANGE */
        unique case (c_LFSR_BITS)
            7: xor_gate = current_state[6] ^ current_state[5];
            15: xor_gate = current_state[14] ^ current_state[13];
            23: xor_gate = current_state[22] ^ current_state[17];
            31: xor_gate = current_state[30] ^ current_state[27];
            default: xor_gate = 1'b0;   
        endcase
        /* verilator lint_on SELRANGE */
        return {current_state[c_LFSR_BITS-2:0], xor_gate};
    endfunction

    p_last_bit_sent_correctly: assert property (@(posedge r_tb_clock) UUT.lfsr_bits[c_LFSR_BITS-1] == r_tb_last_lfsr_bit) 
    else $error("%0t: LFSR did not send last bit correctly: expected %b, got %b", $time, UUT.lfsr_bits[c_LFSR_BITS-1], r_tb_last_lfsr_bit);

    initial begin
        assert (c_LFSR_BITS inside {7, 31}) else $error("Unsupported value of c_LFSR_BITS");

        $dumpfile("lfsr_tb.vcd");
        $dumpvars(0, lfsr_tb);
        // check reset (active-low!) to default seed value
        r_tb_reset <= 1'b0;
        @(posedge r_tb_clock);
        #c_WAIT_FOR_SIGNALS_TO_SETTLE;
        a_reset_to_default_seed: assert (UUT.lfsr_bits == UUT.c_LFSR_SEED) 
        else $error("%0t: LFSR was not seeded correctly upon reset: expected %b, got %b", $time, UUT.c_LFSR_SEED, UUT.lfsr_bits);
        r_tb_reset <= 1'b1;
        @(posedge r_tb_clock);

        // test bit loading
        r_tb_load_enable <= 1'b1;
        @(posedge r_tb_clock);
        r_tb_expected_next_state <= {UUT.lfsr_bits[c_LFSR_BITS-2:0], r_tb_load_bit};
        #c_WAIT_FOR_SIGNALS_TO_SETTLE;
        a_load_bit_to_lfsr: assert (UUT.lfsr_bits == r_tb_expected_next_state)
        else $error("%0t: LFSR bits do not match bits expected from contenating with loaded bit: expected %b, got %b",
        $time, UUT.lfsr_bits, r_tb_expected_next_state);
        @(posedge r_tb_clock);
        r_tb_load_enable <= 1'b0;
        @(posedge r_tb_clock);

        // check that output is based on XOR tap
        repeat(2*c_LFSR_BITS) begin
            @(posedge r_tb_clock);
            r_tb_expected_next_state <= get_next_state(UUT.lfsr_bits); 
            #c_WAIT_FOR_SIGNALS_TO_SETTLE;
            a_xor_appended_correctly: assert (r_tb_expected_next_state == UUT.lfsr_bits) 
            else $error("%0t: LFSR bits do not match bits expected from contenating with XOR gate outputs", $time);
        end

        // check that there are 2^{c_LFSR_BITS} - 1 unique, non-zero states
        // reset to start counting from seed
        r_tb_reset <= 1'b0;
        @(posedge r_tb_clock);
        r_tb_reset <= 1'b1;
        @(posedge r_tb_clock);

        // state should now be the seed value
        begin
            automatic bit seen_states [logic [c_LFSR_BITS-1:0]]; // store true\false values per LFSR state, accessed via LFSR state
            for (int i = 1; i < c_LFSR_PERIOD; i++) begin
                a_nonzero_state: assert (UUT.lfsr_bits != '0) else $error("%0t: LFSR in illegal all-zero state", $time);
                a_state_not_seen_before: assert (!seen_states.exists(UUT.lfsr_bits)) 
                else $error("%0t: LFSR state already seen before LFSR period exceeded: %b (iteration %d)", $time, UUT.lfsr_bits, i);
                seen_states[UUT.lfsr_bits] = 1'b1;
                @(posedge r_tb_clock);
                #c_WAIT_FOR_SIGNALS_TO_SETTLE;
                $display(UUT.lfsr_bits);
            end
            $display(UUT.lfsr_bits);
            $display(UUT.c_LFSR_SEED);
            a_return_to_seed: assert (UUT.lfsr_bits == UUT.c_LFSR_SEED) 
            else $error("%0t: LFSR bits did not cycle back to seed value after LFSR period", $time);
        end

        $display("%0t: SUCCESS: all checks passed!", $time);
        $finish;
    end

    // In case the UUT hangs and never reaches $finish
    initial begin
        #10000;
        $error("ERROR: testbench timeout");
        $finish;
    end
endmodule

lfsr_tb.vcd
$version Generated by VerilatedVcd $end
$timescale 1ps $end
 $scope module TOP $end
  $scope module lfsr_tb $end
   $var wire 32 ) c_LFSR_BITS [31:0] $end
   $var wire 32 * c_LFSR_PERIOD [31:0] $end
   $var wire 32 + c_WAIT_FOR_SIGNALS_TO_SETTLE [31:0] $end
   $var wire 1 % r_tb_clock $end
   $var wire 1 & r_tb_reset $end
   $var wire 1 ' r_tb_load_enable $end
   $var wire 1 , r_tb_load_bit $end
   $var wire 1 " r_tb_last_lfsr_bit $end
   $var wire 7 ( r_tb_expected_next_state [6:0] $end
   $scope module UUT $end
    $var wire 32 - c_LFSR_BITS [31:0] $end
    $var wire 7 . c_LFSR_SEED [6:0] $end
    $var wire 1 % i_clock $end
    $var wire 1 & i_reset $end
    $var wire 1 ' i_load_enable $end
    $var wire 1 , i_load_bit $end
    $var wire 1 " o_last_lfsr_bit $end
    $var wire 7 # lfsr_bits [6:0] $end
    $var wire 1 $ xor_gate $end
   $upscope $end
  $upscope $end
 $upscope $end
$enddefinitions $end


#1
0"
b0000000 #
0$
0%
0&
0'
b0000000 (
b00000000000000000000000000000111 )
b00000000000000000000000001111111 *
b00000000000000000000000000000001 +
0,
b00000000000000000000000000000111 -
b0000001 .
#6
b0000001 #
1%
#7
1&
#11
0%
#16
b0000010 #
1%
1'
#21
0%
#26
b0000100 #
1%
b0000100 (
#31
0%
#36
b0001000 #
1%
0'
#41
0%
#46
b0010000 #
1%
#51
0%
#56
b0100000 #
1$
1%
b0100000 (
#61
0%
#66
1"
b1000001 #
1%
b1000001 (
#71
0%
#76
0"
b0000011 #
0$
1%
b0000011 (
#81
0%
#86
b0000110 #
1%
b0000110 (
#91
0%
#96
b0001100 #
1%
b0001100 (
#101
0%
#106
b0011000 #
1%
b0011000 (
#111
0%
#116
b0110000 #
1$
1%
b0110000 (
#121
0%
#126
1"
b1100001 #
0$
1%
b1100001 (
#131
0%
#136
b1000010 #
1$
1%
b1000010 (
#141
0%
#146
0"
b0000101 #
0$
1%
b0000101 (
#151
0%
#156
b0001010 #
1%
b0001010 (
#161
0%
#166
b0010100 #
1%
b0010100 (
#171
0%
#176
b0101000 #
1$
1%
b0101000 (
#181
0%
#186
1"
b1010001 #
1%
b1010001 (
#187
0&
#191
0%
#196
0"
b0000001 #
0$
1%
1&
#201
0%
#206
b0000010 #
1%
#211
0%
#216
b0000100 #
1%
#221
0%
#226
b0001000 #
1%
#231
0%
#236
b0010000 #
1%
#241
0%
#246
b0100000 #
1$
1%
#251
0%
#256
1"
b1000001 #
1%
#261
0%
#266
0"
b0000011 #
0$
1%
#271
0%
#276
b0000110 #
1%
#281
0%
#286
b0001100 #
1%
#291
0%
#296
b0011000 #
1%
#301
0%
#306
b0110000 #
1$
1%
#311
0%
#316
1"
b1100001 #
0$
1%
#321
0%
#326
b1000010 #
1$
1%
#331
0%
#336
0"
b0000101 #
0$
1%
#341
0%
#346
b0001010 #
1%
#351
0%
#356
b0010100 #
1%
#361
0%
#366
b0101000 #
1$
1%
#371
0%
#376
1"
b1010001 #
1%
#381
0%
#386
0"
b0100011 #
1%
#391
0%
#396
1"
b1000111 #
1%
#401
0%
#406
0"
b0001111 #
0$
1%
#411
0%
#416
b0011110 #
1%
#421
0%
#426
b0111100 #
1$
1%
#431
0%
#436
1"
b1111001 #
0$
1%
#441
0%
#446
b1110010 #
1%
#451
0%
#456
b1100100 #
1%
#461
0%
#466
b1001000 #
1$
1%
#471
0%
#476
0"
b0010001 #
0$
1%
#481
0%
#486
b0100010 #
1$
1%
#491
0%
#496
1"
b1000101 #
1%
#501
0%
#506
0"
b0001011 #
0$
1%
#511
0%
#516
b0010110 #
1%
#521
0%
#526
b0101100 #
1$
1%
#531
0%
#536
1"
b1011001 #
1%
#541
0%
#546
0"
b0110011 #
1%
#551
0%
#556
1"
b1100111 #
0$
1%
#561
0%
#566
b1001110 #
1$
1%
#571
0%
#576
0"
b0011101 #
0$
1%
#581
0%
#586
b0111010 #
1$
1%
#591
0%
#596
1"
b1110101 #
0$
1%
#601
0%
#606
b1101010 #
1%
#611
0%
#616
b1010100 #
1$
1%
#621
0%
#626
0"
b0101001 #
1%
#631
0%
#636
1"
b1010011 #
1%
#641
0%
#646
0"
b0100111 #
1%
#651
0%
#656
1"
b1001111 #
1%
#661
0%
#666
0"
b0011111 #
0$
1%
#671
0%
#676
b0111110 #
1$
1%
#681
0%
#686
1"
b1111101 #
0$
1%
#691
0%
#696
b1111010 #
1%
#701
0%
#706
b1110100 #
1%
#711
0%
#716
b1101000 #
1%
#721
0%
#726
b1010000 #
1$
1%
#731
0%
#736
0"
b0100001 #
1%
#741
0%
#746
1"
b1000011 #
1%
#751
0%
#756
0"
b0000111 #
0$
1%
#761
0%
#766
b0001110 #
1%
#771
0%
#776
b0011100 #
1%
#781
0%
#786
b0111000 #
1$
1%
#791
0%
#796
1"
b1110001 #
0$
1%
#801
0%
#806
b1100010 #
1%
#811
0%
#816
b1000100 #
1$
1%
#821
0%
#826
0"
b0001001 #
0$
1%
#831
0%
#836
b0010010 #
1%
#841
0%
#846
b0100100 #
1$
1%
#851
0%
#856
1"
b1001001 #
1%
#861
0%
#866
0"
b0010011 #
0$
1%
#871
0%
#876
b0100110 #
1$
1%
#881
0%
#886
1"
b1001101 #
1%
#891
0%
#896
0"
b0011011 #
0$
1%
#901
0%
#906
b0110110 #
1$
1%
#911
0%
#916
1"
b1101101 #
0$
1%
#921
0%
#926
b1011010 #
1$
1%
#931
0%
#936
0"
b0110101 #
1%
#941
0%
#946
1"
b1101011 #
0$
1%
#951
0%
#956
b1010110 #
1$
1%
#961
0%
#966
0"
b0101101 #
1%
#971
0%
#976
1"
b1011011 #
1%
#981
0%
#986
0"
b0110111 #
1%
#991
0%
#996
1"
b1101111 #
0$
1%
#1001
0%
#1006
b1011110 #
1$
1%
#1011
0%
#1016
0"
b0111101 #
1%
#1021
0%
#1026
1"
b1111011 #
0$
1%
#1031
0%
#1036
b1110110 #
1%
#1041
0%
#1046
b1101100 #
1%
#1051
0%
#1056
b1011000 #
1$
1%
#1061
0%
#1066
0"
b0110001 #
1%
#1071
0%
#1076
1"
b1100011 #
0$
1%
#1081
0%
#1086
b1000110 #
1$
1%
#1091
0%
#1096
0"
b0001101 #
0$
1%
#1101
0%
#1106
b0011010 #
1%
#1111
0%
#1116
b0110100 #
1$
1%
#1121
0%
#1126
1"
b1101001 #
0$
1%
#1131
0%
#1136
b1010010 #
1$
1%
#1141
0%
#1146
0"
b0100101 #
1%
#1151
0%
#1156
1"
b1001011 #
1%
#1161
0%
#1166
0"
b0010111 #
0$
1%
#1171
0%
#1176
b0101110 #
1$
1%
#1181
0%
#1186
1"
b1011101 #
1%
#1191
0%
#1196
0"
b0111011 #
1%
#1201
0%
#1206
1"
b1110111 #
0$
1%
#1211
0%
#1216
b1101110 #
1%
#1221
0%
#1226
b1011100 #
1$
1%
#1231
0%
#1236
0"
b0111001 #
1%
#1241
0%
#1246
1"
b1110011 #
0$
1%
#1251
0%
#1256
b1100110 #
1%
#1261
0%
#1266
b1001100 #
1$
1%
#1271
0%
#1276
0"
b0011001 #
0$
1%
#1281
0%
#1286
b0110010 #
1$
1%
#1291
0%
#1296
1"
b1100101 #
0$
1%
#1301
0%
#1306
b1001010 #
1$
1%
#1311
0%
#1316
0"
b0010101 #
0$
1%
#1321
0%
#1326
b0101010 #
1$
1%
#1331
0%
#1336
1"
b1010101 #
1%
#1341
0%
#1346
0"
b0101011 #
1%
#1351
0%
#1356
1"
b1010111 #
1%
#1361
0%
#1366
0"
b0101111 #
1%
#1371
0%
#1376
1"
b1011111 #
1%
#1381
0%
#1386
0"
b0111111 #
1%
#1391
0%
#1396
1"
b1111111 #
0$
1%
#1401
0%
#1406
b1111110 #
1%
#1411
0%
#1416
b1111100 #
1%
#1421
0%
#1426
b1111000 #
1%
#1431
0%
#1436
b1110000 #
1%
#1441
0%
#1446
b1100000 #
1%
#1451
0%
#1456
b1000000 #
1$
1%
#1461
0%
#1466
0"
b0000001 #
0$
1%
